[
  {
  "description":"模拟一个返回cookies的GET请求",
  "request":{
  "uri":"/getcookies",
  "method":"get"
  },
  "response":{
  "headers":{ "Content-Type":"text/html;charset=gbk" },
  "cookies":{
  "login":"true"
  },
  "text":"成功获取cookies"
  }
  },
  {
 "description":"模拟一个有参数Cookies的POST请求",
    "request":{
      "uri":"/postcookiesdemo",
      "method":"post",
      "forms":{
      "name":"yyl",
      "age":"22"
      },
      "cookies":{
      "login":"true"
      }
    },
    "response":
    {
    "headers":{ "Content-Type":"text/html;charset=gbk" },
    "status":200,
    "json":{
    "yyl":"success",
    "status":"1"
    }
    }
  }
  ]